odoo/addons/currency_rate_update_TH_BOT/README.rst
odoo/addons/currency_rate_update_TH_BOT/__init__.py
odoo/addons/currency_rate_update_TH_BOT/__manifest__.py
odoo/addons/currency_rate_update_TH_BOT/data/config_parameter.xml
odoo/addons/currency_rate_update_TH_BOT/i18n/currency_rate_update_TH_BOT.pot
odoo/addons/currency_rate_update_TH_BOT/models/__init__.py
odoo/addons/currency_rate_update_TH_BOT/models/res_company.py
odoo/addons/currency_rate_update_TH_BOT/models/res_config_settings.py
odoo/addons/currency_rate_update_TH_BOT/models/res_currency.py
odoo/addons/currency_rate_update_TH_BOT/models/res_currency_rate_provider_BOT.py
odoo/addons/currency_rate_update_TH_BOT/readme/CONFIGURE.md
odoo/addons/currency_rate_update_TH_BOT/readme/CONTRIBUTORS.md
odoo/addons/currency_rate_update_TH_BOT/readme/DESCRIPTION.md
odoo/addons/currency_rate_update_TH_BOT/readme/USAGE.md
odoo/addons/currency_rate_update_TH_BOT/static/description/icon.png
odoo/addons/currency_rate_update_TH_BOT/static/description/index.html
odoo/addons/currency_rate_update_TH_BOT/tests/__init__.py
odoo/addons/currency_rate_update_TH_BOT/tests/test_currency_rate_update_TH_BOT.py
odoo/addons/currency_rate_update_TH_BOT/views/res_config_settings.xml
odoo/addons/currency_rate_update_TH_BOT/views/res_currency_rate_provider.xml
odoo/addons/currency_rate_update_TH_BOT/views/res_currency_views.xml
odoo_addon_currency_rate_update_th_bot-17.0.1.0.0.2.dist-info/METADATA
odoo_addon_currency_rate_update_th_bot-17.0.1.0.0.2.dist-info/WHEEL
odoo_addon_currency_rate_update_th_bot-17.0.1.0.0.2.dist-info/top_level.txt
odoo_addon_currency_rate_update_th_bot-17.0.1.0.0.2.dist-info/RECORD
